{
  "state": 0,
  "message": "查询成功",
  "total": 1937,
  "pageNum": 65,
  "pageNo": 2,
  "pageSize": 30,
  "Tflag": 0,
  "result": [
    {
      "name": "双色球",
      "code": "2025100",
      "detailsLink": "/c/2025/08/31/626614.shtml",
      "videoLink": "/c/2025/08/31/626618.shtml",
      "date": "2025-08-31(日)",
      "week": "日",
      "red": "12,16,17,25,30,31",
      "blue": "16",
      "blue2": "",
      "sales": "383791808",
      "poolmoney": "2597220563",
      "content": "北京1注，黑龙江1注，江苏1注，山东2注，广东6注，共11注。",
      "addmoney": "",
      "addmoney2": "",
      "msg": "",
      "z2add": "",
      "m2add": "",
      "prizegrades": [
        { "type": 1, "typenum": "11", "typemoney": "7099632" },
        { "type": 2, "typenum": "107", "typemoney": "269812" },
        { "type": 3, "typenum": "1110", "typemoney": "3000" },
        { "type": 4, "typenum": "59088", "typemoney": "200" },
        { "type": 5, "typenum": "1209679", "typemoney": "10" },
        { "type": 6, "typenum": "9066765", "typemoney": "5" },
        { "type": 7, "typenum": "", "typemoney": "" }
      ]
    },
    {
      "name": "双色球",
      "code": "2025099",
      "detailsLink": "/c/2025/08/28/626395.shtml",
      "videoLink": "/c/2025/08/28/626399.shtml",
      "date": "2025-08-28(四)",
      "week": "四",
      "red": "09,11,15,17,22,26",
      "blue": "14",
      "blue2": "",
      "sales": "353036232",
      "poolmoney": "2588706689",
      "content": "江苏1注，河南1注，共2注。",
      "addmoney": "",
      "addmoney2": "",
      "msg": "",
      "z2add": "",
      "m2add": "",
      "prizegrades": [
        { "type": 1, "typenum": "2", "typemoney": "10000000" },
        { "type": 2, "typenum": "155", "typemoney": "193182" },
        { "type": 3, "typenum": "1018", "typemoney": "3000" },
        { "type": 4, "typenum": "54648", "typemoney": "200" },
        { "type": 5, "typenum": "1169699", "typemoney": "10" },
        { "type": 6, "typenum": "5506819", "typemoney": "5" },
        { "type": 7, "typenum": "", "typemoney": "" }
      ]
    },
    {
      "name": "双色球",
      "code": "2025098",
      "detailsLink": "/c/2025/08/26/626181.shtml",
      "videoLink": "/c/2025/08/26/626185.shtml",
      "date": "2025-08-26(二)",
      "week": "二",
      "red": "05,08,13,17,18,29",
      "blue": "02",
      "blue2": "",
      "sales": "348777356",
      "poolmoney": "2518876889",
      "content": "河北1注，山西1注，内蒙古1注，上海1注，浙江1注，安徽1注，福建1注，山东2注，重庆1注，湖北3注，湖南1注，广东5注，广西1注，宁夏2注，共22注。",
      "addmoney": "",
      "addmoney2": "",
      "msg": "",
      "z2add": "",
      "m2add": "",
      "prizegrades": [
        { "type": 1, "typenum": "22", "typemoney": "5510882" },
        { "type": 2, "typenum": "269", "typemoney": "52227" },
        { "type": 3, "typenum": "3274", "typemoney": "3000" },
        { "type": 4, "typenum": "131148", "typemoney": "200" },
        { "type": 5, "typenum": "1962611", "typemoney": "10" },
        { "type": 6, "typenum": "11805233", "typemoney": "5" },
        { "type": 7, "typenum": "", "typemoney": "" }
      ]
    },
    {
      "name": "双色球",
      "code": "2025097",
      "detailsLink": "/c/2025/08/24/625967.shtml",
      "videoLink": "/c/2025/08/24/625971.shtml",
      "date": "2025-08-24(日)",
      "week": "日",
      "red": "03,05,16,23,26,31",
      "blue": "14",
      "blue2": "",
      "sales": "380958632",
      "poolmoney": "2597968523",
      "content": "宁夏1注，深圳1注，共2注。",
      "addmoney": "",
      "addmoney2": "",
      "msg": "",
      "z2add": "",
      "m2add": "",
      "prizegrades": [
        { "type": 1, "typenum": "2", "typemoney": "10000000" },
        { "type": 2, "typenum": "178", "typemoney": "161344" },
        { "type": 3, "typenum": "921", "typemoney": "3000" },
        { "type": 4, "typenum": "58945", "typemoney": "200" },
        { "type": 5, "typenum": "1244528", "typemoney": "10" },
        { "type": 6, "typenum": "8959038", "typemoney": "5" },
        { "type": 7, "typenum": "", "typemoney": "" }
      ]
    },
    {
      "name": "双色球",
      "code": "2025096",
      "detailsLink": "/c/2025/08/21/625848.shtml",
      "videoLink": "/c/2025/08/21/625853.shtml",
      "date": "2025-08-21(四)",
      "week": "四",
      "red": "07,09,11,12,16,29",
      "blue": "15",
      "blue2": "",
      "sales": "350353036",
      "poolmoney": "2531810580",
      "content": "广东1注，共1注。",
      "addmoney": "",
      "addmoney2": "",
      "msg": "",
      "z2add": "",
      "m2add": "",
      "prizegrades": [
        { "type": 1, "typenum": "1", "typemoney": "10000000" },
        { "type": 2, "typenum": "165", "typemoney": "148472" },
        { "type": 3, "typenum": "1273", "typemoney": "3000" },
        { "type": 4, "typenum": "78084", "typemoney": "200" },
        { "type": 5, "typenum": "1489125", "typemoney": "10" },
        { "type": 6, "typenum": "7870820", "typemoney": "5" },
        { "type": 7, "typenum": "", "typemoney": "" }
      ]
    },
    {
      "name": "双色球",
      "code": "2025095",
      "detailsLink": "/c/2025/08/19/625534.shtml",
      "videoLink": "/c/2025/08/19/625538.shtml",
      "date": "2025-08-19(二)",
      "week": "二",
      "red": "15,16,22,23,26,32",
      "blue": "04",
      "blue2": "",
      "sales": "347483168",
      "poolmoney": "2468316703",
      "content": "北京2注，黑龙江1注，山东2注，湖北1注，云南1注，新疆1注，共8注。",
      "addmoney": "",
      "addmoney2": "",
      "msg": "",
      "z2add": "",
      "m2add": "",
      "prizegrades": [
        { "type": 1, "typenum": "8", "typemoney": "7368773" },
        { "type": 2, "typenum": "78", "typemoney": "303688" },
        { "type": 3, "typenum": "1751", "typemoney": "3000" },
        { "type": 4, "typenum": "65043", "typemoney": "200" },
        { "type": 5, "typenum": "1183058", "typemoney": "10" },
        { "type": 6, "typenum": "9084729", "typemoney": "5" },
        { "type": 7, "typenum": "", "typemoney": "" }
      ]
    },
    {
      "name": "双色球",
      "code": "2025094",
      "detailsLink": "/c/2025/08/17/625320.shtml",
      "videoLink": "/c/2025/08/17/625322.shtml",
      "date": "2025-08-17(日)",
      "week": "日",
      "red": "11,13,17,19,23,29",
      "blue": "16",
      "blue2": "",
      "sales": "378464962",
      "poolmoney": "2456203693",
      "content": "北京1注，上海1注，安徽2注，山东1注，重庆1注，广西1注，陕西1注，共8注。",
      "addmoney": "",
      "addmoney2": "",
      "msg": "",
      "z2add": "",
      "m2add": "",
      "prizegrades": [
        { "type": 1, "typenum": "8", "typemoney": "7778083" },
        { "type": 2, "typenum": "196", "typemoney": "141738" },
        { "type": 3, "typenum": "1167", "typemoney": "3000" },
        { "type": 4, "typenum": "60717", "typemoney": "200" },
        { "type": 5, "typenum": "1180957", "typemoney": "10" },
        { "type": 6, "typenum": "9374101", "typemoney": "5" },
        { "type": 7, "typenum": "", "typemoney": "" }
      ]
    },
    {
      "name": "双色球",
      "code": "2025093",
      "detailsLink": "/c/2025/08/14/625201.shtml",
      "videoLink": "/c/2025/08/14/625205.shtml",
      "date": "2025-08-14(四)",
      "week": "四",
      "red": "09,11,12,24,25,26",
      "blue": "10",
      "blue2": "",
      "sales": "356349402",
      "poolmoney": "2435085847",
      "content": "北京1注，江苏3注，浙江1注，安徽1注，山东1注，河南2注，广东2注，深圳1注，共12注。",
      "addmoney": "",
      "addmoney2": "",
      "msg": "",
      "z2add": "",
      "m2add": "",
      "prizegrades": [
        { "type": 1, "typenum": "12", "typemoney": "6161412" },
        { "type": 2, "typenum": "136", "typemoney": "128096" },
        { "type": 3, "typenum": "2241", "typemoney": "3000" },
        { "type": 4, "typenum": "89801", "typemoney": "200" },
        { "type": 5, "typenum": "1488101", "typemoney": "10" },
        { "type": 6, "typenum": "13072454", "typemoney": "5" },
        { "type": 7, "typenum": "", "typemoney": "" }
      ]
    },
    {
      "name": "双色球",
      "code": "2025092",
      "detailsLink": "/c/2025/08/12/624987.shtml",
      "videoLink": "/c/2025/08/12/624991.shtml",
      "date": "2025-08-12(二)",
      "week": "二",
      "red": "02,11,14,17,23,24",
      "blue": "12",
      "blue2": "",
      "sales": "350909082",
      "poolmoney": "2456759248",
      "content": "辽宁1注，上海2注，安徽1注，广东1注，广西1注，陕西1注，共7注。",
      "addmoney": "",
      "addmoney2": "",
      "msg": "",
      "z2add": "",
      "m2add": "",
      "prizegrades": [
        { "type": 1, "typenum": "7", "typemoney": "7508266" },
        { "type": 2, "typenum": "110", "typemoney": "199521" },
        { "type": 3, "typenum": "2335", "typemoney": "3000" },
        { "type": 4, "typenum": "77648", "typemoney": "200" },
        { "type": 5, "typenum": "1336930", "typemoney": "10" },
        { "type": 6, "typenum": "9650446", "typemoney": "5" },
        { "type": 7, "typenum": "", "typemoney": "" }
      ]
    },
    {
      "name": "双色球",
      "code": "2025091",
      "detailsLink": "/c/2025/08/10/624773.shtml",
      "videoLink": "/c/2025/08/10/624775.shtml",
      "date": "2025-08-10(日)",
      "week": "日",
      "red": "03,04,17,19,25,27",
      "blue": "14",
      "blue2": "",
      "sales": "381527438",
      "poolmoney": "2443475122",
      "content": "吉林1注，上海2注，浙江1注，重庆1注，湖南3注，共8注。",
      "addmoney": "",
      "addmoney2": "",
      "msg": "",
      "z2add": "",
      "m2add": "",
      "prizegrades": [
        { "type": 1, "typenum": "8", "typemoney": "7525259" },
        { "type": 2, "typenum": "114", "typemoney": "221513" },
        { "type": 3, "typenum": "1482", "typemoney": "3000" },
        { "type": 4, "typenum": "72866", "typemoney": "200" },
        { "type": 5, "typenum": "1433351", "typemoney": "10" },
        { "type": 6, "typenum": "10517074", "typemoney": "5" },
        { "type": 7, "typenum": "", "typemoney": "" }
      ]
    },
    {
      "name": "双色球",
      "code": "2025090",
      "detailsLink": "/c/2025/08/07/624654.shtml",
      "videoLink": "/c/2025/08/07/624658.shtml",
      "date": "2025-08-07(四)",
      "week": "四",
      "red": "06,11,12,21,27,28",
      "blue": "15",
      "blue2": "",
      "sales": "358843770",
      "poolmoney": "2427919422",
      "content": "黑龙江1注，上海1注，河南2注，湖北40注，湖南3注，广东1注，云南2注，新疆1注，共51注。",
      "addmoney": "",
      "addmoney2": "",
      "msg": "",
      "z2add": "",
      "m2add": "",
      "prizegrades": [
        { "type": 1, "typenum": "51", "typemoney": "5406061" },
        { "type": 2, "typenum": "197", "typemoney": "131403" },
        { "type": 3, "typenum": "1623", "typemoney": "3000" },
        { "type": 4, "typenum": "74536", "typemoney": "200" },
        { "type": 5, "typenum": "1392709", "typemoney": "10" },
        { "type": 6, "typenum": "7716891", "typemoney": "5" },
        { "type": 7, "typenum": "", "typemoney": "" }
      ]
    },
    {
      "name": "双色球",
      "code": "2025089",
      "detailsLink": "/c/2025/08/05/624440.shtml",
      "videoLink": "/c/2025/08/05/624445.shtml",
      "date": "2025-08-05(二)",
      "week": "二",
      "red": "04,06,08,18,31,33",
      "blue": "05",
      "blue2": "",
      "sales": "346126366",
      "poolmoney": "2625969286",
      "content": "浙江1注，福建2注，云南1注，新疆1注，共5注。",
      "addmoney": "",
      "addmoney2": "",
      "msg": "",
      "z2add": "",
      "m2add": "",
      "prizegrades": [
        { "type": 1, "typenum": "5", "typemoney": "8555036" },
        { "type": 2, "typenum": "82", "typemoney": "270963" },
        { "type": 3, "typenum": "1309", "typemoney": "3000" },
        { "type": 4, "typenum": "67216", "typemoney": "200" },
        { "type": 5, "typenum": "1293962", "typemoney": "10" },
        { "type": 6, "typenum": "10083237", "typemoney": "5" },
        { "type": 7, "typenum": "", "typemoney": "" }
      ]
    },
    {
      "name": "双色球",
      "code": "2025088",
      "detailsLink": "/c/2025/08/03/624226.shtml",
      "videoLink": "/c/2025/08/03/624230.shtml",
      "date": "2025-08-03(日)",
      "week": "日",
      "red": "01,03,13,18,21,25",
      "blue": "06",
      "blue2": "",
      "sales": "378870024",
      "poolmoney": "2602087534",
      "content": "上海1注，浙江1注，安徽1注，甘肃1注，共4注。",
      "addmoney": "",
      "addmoney2": "",
      "msg": "",
      "z2add": "",
      "m2add": "",
      "prizegrades": [
        { "type": 1, "typenum": "4", "typemoney": "10000000" },
        { "type": 2, "typenum": "68", "typemoney": "404098" },
        { "type": 3, "typenum": "1049", "typemoney": "3000" },
        { "type": 4, "typenum": "57649", "typemoney": "200" },
        { "type": 5, "typenum": "1285134", "typemoney": "10" },
        { "type": 6, "typenum": "9640694", "typemoney": "5" },
        { "type": 7, "typenum": "", "typemoney": "" }
      ]
    },
    {
      "name": "双色球",
      "code": "2025087",
      "detailsLink": "/c/2025/07/31/624107.shtml",
      "videoLink": "/c/2025/07/31/624109.shtml",
      "date": "2025-07-31(四)",
      "week": "四",
      "red": "02,06,14,15,24,26",
      "blue": "08",
      "blue2": "",
      "sales": "350994188",
      "poolmoney": "2559651509",
      "content": "福建1注，江西1注，广东1注，共3注。",
      "addmoney": "",
      "addmoney2": "",
      "msg": "",
      "z2add": "",
      "m2add": "",
      "prizegrades": [
        { "type": 1, "typenum": "3", "typemoney": "9688475" },
        { "type": 2, "typenum": "105", "typemoney": "167445" },
        { "type": 3, "typenum": "1642", "typemoney": "3000" },
        { "type": 4, "typenum": "77961", "typemoney": "200" },
        { "type": 5, "typenum": "1354571", "typemoney": "10" },
        { "type": 6, "typenum": "13519223", "typemoney": "5" },
        { "type": 7, "typenum": "", "typemoney": "" }
      ]
    },
    {
      "name": "双色球",
      "code": "2025086",
      "detailsLink": "/c/2025/07/29/623893.shtml",
      "videoLink": "/c/2025/07/29/623897.shtml",
      "date": "2025-07-29(二)",
      "week": "二",
      "red": "02,06,08,10,17,24",
      "blue": "06",
      "blue2": "",
      "sales": "345276906",
      "poolmoney": "2535971590",
      "content": "黑龙江1注，上海2注，浙江1注，山东2注，河南1注，湖南3注，甘肃5注，青海1注，共16注。",
      "addmoney": "",
      "addmoney2": "",
      "msg": "",
      "z2add": "",
      "m2add": "",
      "prizegrades": [
        { "type": 1, "typenum": "16", "typemoney": "5994098" },
        { "type": 2, "typenum": "118", "typemoney": "168491" },
        { "type": 3, "typenum": "1660", "typemoney": "3000" },
        { "type": 4, "typenum": "83526", "typemoney": "200" },
        { "type": 5, "typenum": "1422037", "typemoney": "10" },
        { "type": 6, "typenum": "10750443", "typemoney": "5" },
        { "type": 7, "typenum": "", "typemoney": "" }
      ]
    },
    {
      "name": "双色球",
      "code": "2025085",
      "detailsLink": "/c/2025/07/27/623479.shtml",
      "videoLink": "/c/2025/07/27/623483.shtml",
      "date": "2025-07-27(日)",
      "week": "日",
      "red": "11,14,15,18,21,24",
      "blue": "13",
      "blue2": "",
      "sales": "373432674",
      "poolmoney": "2572231246",
      "content": "广东1注，云南11注，陕西5注，共17注。",
      "addmoney": "",
      "addmoney2": "",
      "msg": "",
      "z2add": "",
      "m2add": "",
      "prizegrades": [
        { "type": 1, "typenum": "17", "typemoney": "6339546" },
        { "type": 2, "typenum": "93", "typemoney": "306079" },
        { "type": 3, "typenum": "847", "typemoney": "3000" },
        { "type": 4, "typenum": "46701", "typemoney": "200" },
        { "type": 5, "typenum": "983135", "typemoney": "10" },
        { "type": 6, "typenum": "9481601", "typemoney": "5" },
        { "type": 7, "typenum": "", "typemoney": "" }
      ]
    },
    {
      "name": "双色球",
      "code": "2025084",
      "detailsLink": "/c/2025/07/24/623060.shtml",
      "videoLink": "/c/2025/07/24/623065.shtml",
      "date": "2025-07-24(四)",
      "week": "四",
      "red": "06,08,10,14,24,33",
      "blue": "15",
      "blue2": "",
      "sales": "350903250",
      "poolmoney": "2594607446",
      "content": "北京1注，内蒙古2注，重庆1注，云南1注，深圳1注，共6注。",
      "addmoney": "",
      "addmoney2": "",
      "msg": "",
      "z2add": "",
      "m2add": "",
      "prizegrades": [
        { "type": 1, "typenum": "6", "typemoney": "8609555" },
        { "type": 2, "typenum": "120", "typemoney": "225597" },
        { "type": 3, "typenum": "1100", "typemoney": "3000" },
        { "type": 4, "typenum": "55779", "typemoney": "200" },
        { "type": 5, "typenum": "1079023", "typemoney": "10" },
        { "type": 6, "typenum": "7681980", "typemoney": "5" },
        { "type": 7, "typenum": "", "typemoney": "" }
      ]
    },
    {
      "name": "双色球",
      "code": "2025083",
      "detailsLink": "/c/2025/07/22/622746.shtml",
      "videoLink": "/c/2025/07/22/622748.shtml",
      "date": "2025-07-22(二)",
      "week": "二",
      "red": "10,15,16,17,27,29",
      "blue": "12",
      "blue2": "",
      "sales": "352801672",
      "poolmoney": "2565049782",
      "content": "浙江1注，山东1注，河南1注，湖北1注，湖南1注，广东1注，四川1注，深圳1注，共8注。",
      "addmoney": "",
      "addmoney2": "",
      "msg": "",
      "z2add": "",
      "m2add": "",
      "prizegrades": [
        { "type": 1, "typenum": "8", "typemoney": "7106890" },
        { "type": 2, "typenum": "145", "typemoney": "145302" },
        { "type": 3, "typenum": "1626", "typemoney": "3000" },
        { "type": 4, "typenum": "79044", "typemoney": "200" },
        { "type": 5, "typenum": "1378454", "typemoney": "10" },
        { "type": 6, "typenum": "10825172", "typemoney": "5" },
        { "type": 7, "typenum": "", "typemoney": "" }
      ]
    },
    {
      "name": "双色球",
      "code": "2025082",
      "detailsLink": "/c/2025/07/20/622532.shtml",
      "videoLink": "/c/2025/07/20/622536.shtml",
      "date": "2025-07-20(日)",
      "week": "日",
      "red": "04,06,09,14,32,33",
      "blue": "11",
      "blue2": "",
      "sales": "378156970",
      "poolmoney": "2558698192",
      "content": "浙江1注，江西1注，山东1注，云南1注，共4注。",
      "addmoney": "",
      "addmoney2": "",
      "msg": "",
      "z2add": "",
      "m2add": "",
      "prizegrades": [
        { "type": 1, "typenum": "4", "typemoney": "9506526" },
        { "type": 2, "typenum": "120", "typemoney": "187771" },
        { "type": 3, "typenum": "1587", "typemoney": "3000" },
        { "type": 4, "typenum": "76384", "typemoney": "200" },
        { "type": 5, "typenum": "1428721", "typemoney": "10" },
        { "type": 6, "typenum": "12168274", "typemoney": "5" },
        { "type": 7, "typenum": "", "typemoney": "" }
      ]
    },
    {
      "name": "双色球",
      "code": "2025081",
      "detailsLink": "/c/2025/07/17/622413.shtml",
      "videoLink": "/c/2025/07/17/622416.shtml",
      "date": "2025-07-17(四)",
      "week": "四",
      "red": "03,06,18,20,23,28",
      "blue": "05",
      "blue2": "",
      "sales": "353894972",
      "poolmoney": "2529126398",
      "content": "浙江2注，广东2注，四川1注，青海1注，共6注。",
      "addmoney": "",
      "addmoney2": "",
      "msg": "",
      "z2add": "",
      "m2add": "",
      "prizegrades": [
        { "type": 1, "typenum": "6", "typemoney": "8415835" },
        { "type": 2, "typenum": "149", "typemoney": "171938" },
        { "type": 3, "typenum": "1441", "typemoney": "3000" },
        { "type": 4, "typenum": "69116", "typemoney": "200" },
        { "type": 5, "typenum": "1384259", "typemoney": "10" },
        { "type": 6, "typenum": "7788936", "typemoney": "5" },
        { "type": 7, "typenum": "", "typemoney": "" }
      ]
    },
    {
      "name": "双色球",
      "code": "2025080",
      "detailsLink": "/c/2025/07/15/622199.shtml",
      "videoLink": "/c/2025/07/15/622201.shtml",
      "date": "2025-07-15(二)",
      "week": "二",
      "red": "03,07,08,10,16,19",
      "blue": "05",
      "blue2": "",
      "sales": "350614738",
      "poolmoney": "2502765112",
      "content": "北京1注，内蒙古1注，江苏1注，安徽1注，湖北1注，广东2注，广西2注，四川2注，云南1注，新疆1注，共13注。",
      "addmoney": "",
      "addmoney2": "",
      "msg": "",
      "z2add": "",
      "m2add": "",
      "prizegrades": [
        { "type": 1, "typenum": "13", "typemoney": "6390774" },
        { "type": 2, "typenum": "180", "typemoney": "125556" },
        { "type": 3, "typenum": "1841", "typemoney": "3000" },
        { "type": 4, "typenum": "89676", "typemoney": "200" },
        { "type": 5, "typenum": "1629711", "typemoney": "10" },
        { "type": 6, "typenum": "8329117", "typemoney": "5" },
        { "type": 7, "typenum": "", "typemoney": "" }
      ]
    },
    {
      "name": "双色球",
      "code": "2025079",
      "detailsLink": "/c/2025/07/13/621885.shtml",
      "videoLink": "/c/2025/07/13/621887.shtml",
      "date": "2025-07-13(日)",
      "week": "日",
      "red": "08,11,14,15,30,32",
      "blue": "05",
      "blue2": "",
      "sales": "380647944",
      "poolmoney": "2518044933",
      "content": "浙江2注，广东3注，云南1注，共6注。",
      "addmoney": "",
      "addmoney2": "",
      "msg": "",
      "z2add": "",
      "m2add": "",
      "prizegrades": [
        { "type": 1, "typenum": "6", "typemoney": "8447936" },
        { "type": 2, "typenum": "107", "typemoney": "241677" },
        { "type": 3, "typenum": "943", "typemoney": "3000" },
        { "type": 4, "typenum": "55057", "typemoney": "200" },
        { "type": 5, "typenum": "1173320", "typemoney": "10" },
        { "type": 6, "typenum": "11501160", "typemoney": "5" },
        { "type": 7, "typenum": "", "typemoney": "" }
      ]
    },
    {
      "name": "双色球",
      "code": "2025078",
      "detailsLink": "/c/2025/07/10/621666.shtml",
      "videoLink": "/c/2025/07/10/621670.shtml",
      "date": "2025-07-10(四)",
      "week": "四",
      "red": "06,15,17,30,32,33",
      "blue": "14",
      "blue2": "",
      "sales": "350559496",
      "poolmoney": "2491153983",
      "content": "共0注。",
      "addmoney": "",
      "addmoney2": "",
      "msg": "",
      "z2add": "",
      "m2add": "",
      "prizegrades": [
        { "type": 1, "typenum": "0", "typemoney": "0" },
        { "type": 2, "typenum": "111", "typemoney": "237198" },
        { "type": 3, "typenum": "883", "typemoney": "3000" },
        { "type": 4, "typenum": "54915", "typemoney": "200" },
        { "type": 5, "typenum": "1046565", "typemoney": "10" },
        { "type": 6, "typenum": "8472114", "typemoney": "5" },
        { "type": 7, "typenum": "", "typemoney": "" }
      ]
    },
    {
      "name": "双色球",
      "code": "2025077",
      "detailsLink": "/c/2025/07/08/621452.shtml",
      "videoLink": "/c/2025/07/08/621457.shtml",
      "date": "2025-07-08(二)",
      "week": "二",
      "red": "04,07,08,15,20,21",
      "blue": "15",
      "blue2": "",
      "sales": "354913968",
      "poolmoney": "2412167034",
      "content": "河北2注，内蒙古1注，安徽2注，湖南2注，广西1注，四川1注，共9注。",
      "addmoney": "",
      "addmoney2": "",
      "msg": "",
      "z2add": "",
      "m2add": "",
      "prizegrades": [
        { "type": 1, "typenum": "9", "typemoney": "7448353" },
        { "type": 2, "typenum": "153", "typemoney": "180025" },
        { "type": 3, "typenum": "1384", "typemoney": "3000" },
        { "type": 4, "typenum": "66249", "typemoney": "200" },
        { "type": 5, "typenum": "1300197", "typemoney": "10" },
        { "type": 6, "typenum": "6665636", "typemoney": "5" },
        { "type": 7, "typenum": "", "typemoney": "" }
      ]
    },
    {
      "name": "双色球",
      "code": "2025076",
      "detailsLink": "/c/2025/07/06/620738.shtml",
      "videoLink": "/c/2025/07/06/620740.shtml",
      "date": "2025-07-06(日)",
      "week": "日",
      "red": "02,06,09,12,14,30",
      "blue": "08",
      "blue2": "",
      "sales": "380376886",
      "poolmoney": "2396570293",
      "content": "广东1注，云南3注，共4注。",
      "addmoney": "",
      "addmoney2": "",
      "msg": "",
      "z2add": "",
      "m2add": "",
      "prizegrades": [
        { "type": 1, "typenum": "4", "typemoney": "7403293" },
        { "type": 2, "typenum": "189", "typemoney": "63579" },
        { "type": 3, "typenum": "2004", "typemoney": "3000" },
        { "type": 4, "typenum": "104084", "typemoney": "200" },
        { "type": 5, "typenum": "1799565", "typemoney": "10" },
        { "type": 6, "typenum": "18698870", "typemoney": "5" },
        { "type": 7, "typenum": "", "typemoney": "" }
      ]
    },
    {
      "name": "双色球",
      "code": "2025075",
      "detailsLink": "/c/2025/07/03/620519.shtml",
      "videoLink": "/c/2025/07/03/620521.shtml",
      "date": "2025-07-03(四)",
      "week": "四",
      "red": "10,12,14,19,20,21",
      "blue": "15",
      "blue2": "",
      "sales": "356433094",
      "poolmoney": "2390134063",
      "content": "辽宁1注，江苏2注，江西1注，河南1注，湖北1注，湖南2注，广东3注，四川1注，共12注。",
      "addmoney": "",
      "addmoney2": "",
      "msg": "",
      "z2add": "",
      "m2add": "",
      "prizegrades": [
        { "type": 1, "typenum": "12", "typemoney": "6293619" },
        { "type": 2, "typenum": "175", "typemoney": "110881" },
        { "type": 3, "typenum": "1792", "typemoney": "3000" },
        { "type": 4, "typenum": "88849", "typemoney": "200" },
        { "type": 5, "typenum": "1480052", "typemoney": "10" },
        { "type": 6, "typenum": "11817741", "typemoney": "5" },
        { "type": 7, "typenum": "", "typemoney": "" }
      ]
    },
    {
      "name": "双色球",
      "code": "2025074",
      "detailsLink": "/c/2025/07/01/620305.shtml",
      "videoLink": "/c/2025/07/01/620309.shtml",
      "date": "2025-07-01(二)",
      "week": "二",
      "red": "03,04,12,20,32,33",
      "blue": "13",
      "blue2": "",
      "sales": "357617458",
      "poolmoney": "2407444608",
      "content": "北京1注，山西1注，内蒙古1注，浙江1注，山东1注，共5注。",
      "addmoney": "",
      "addmoney2": "",
      "msg": "",
      "z2add": "",
      "m2add": "",
      "prizegrades": [
        { "type": 1, "typenum": "5", "typemoney": "9211242" },
        { "type": 2, "typenum": "78", "typemoney": "337439" },
        { "type": 3, "typenum": "1220", "typemoney": "3000" },
        { "type": 4, "typenum": "62814", "typemoney": "200" },
        { "type": 5, "typenum": "1145553", "typemoney": "10" },
        { "type": 6, "typenum": "8454630", "typemoney": "5" },
        { "type": 7, "typenum": "", "typemoney": "" }
      ]
    },
    {
      "name": "双色球",
      "code": "2025073",
      "detailsLink": "/c/2025/06/29/619991.shtml",
      "videoLink": "/c/2025/06/29/619995.shtml",
      "date": "2025-06-29(日)",
      "week": "日",
      "red": "02,07,10,27,30,33",
      "blue": "11",
      "blue2": "",
      "sales": "388648778",
      "poolmoney": "2374540018",
      "content": "辽宁1注，上海3注，江苏1注，安徽1注，江西2注，重庆2注，广东3注，广西1注，四川3注，云南2注，共19注。",
      "addmoney": "",
      "addmoney2": "",
      "msg": "",
      "z2add": "",
      "m2add": "",
      "prizegrades": [
        { "type": 1, "typenum": "19", "typemoney": "5914846" },
        { "type": 2, "typenum": "164", "typemoney": "132485" },
        { "type": 3, "typenum": "2984", "typemoney": "3000" },
        { "type": 4, "typenum": "105599", "typemoney": "200" },
        { "type": 5, "typenum": "1627484", "typemoney": "10" },
        { "type": 6, "typenum": "11436168", "typemoney": "5" },
        { "type": 7, "typenum": "", "typemoney": "" }
      ]
    },
    {
      "name": "双色球",
      "code": "2025072",
      "detailsLink": "/c/2025/06/26/619772.shtml",
      "videoLink": "/c/2025/06/26/619774.shtml",
      "date": "2025-06-26(四)",
      "week": "四",
      "red": "02,14,17,25,27,29",
      "blue": "05",
      "blue2": "",
      "sales": "359396990",
      "poolmoney": "2421739287",
      "content": "河北1注，山东1注，湖南5注，深圳1注，共8注。",
      "addmoney": "",
      "addmoney2": "",
      "msg": "",
      "z2add": "",
      "m2add": "",
      "prizegrades": [
        { "type": 1, "typenum": "8", "typemoney": "7489467" },
        { "type": 2, "typenum": "121", "typemoney": "205741" },
        { "type": 3, "typenum": "1247", "typemoney": "3000" },
        { "type": 4, "typenum": "63197", "typemoney": "200" },
        { "type": 5, "typenum": "1229062", "typemoney": "10" },
        { "type": 6, "typenum": "9570965", "typemoney": "5" },
        { "type": 7, "typenum": "", "typemoney": "" }
      ]
    },
    {
      "name": "双色球",
      "code": "2025071",
      "detailsLink": "/c/2025/06/24/619258.shtml",
      "videoLink": "/c/2025/06/24/619260.shtml",
      "date": "2025-06-24(二)",
      "week": "二",
      "red": "01,12,18,23,25,28",
      "blue": "07",
      "blue2": "",
      "sales": "357410052",
      "poolmoney": "2406971013",
      "content": "河北1注，浙江1注，广东1注，共3注。",
      "addmoney": "",
      "addmoney2": "",
      "msg": "",
      "z2add": "",
      "m2add": "",
      "prizegrades": [
        { "type": 1, "typenum": "3", "typemoney": "10000000" },
        { "type": 2, "typenum": "110", "typemoney": "196923" },
        { "type": 3, "typenum": "1495", "typemoney": "3000" },
        { "type": 4, "typenum": "80907", "typemoney": "200" },
        { "type": 5, "typenum": "1362609", "typemoney": "10" },
        { "type": 6, "typenum": "10838449", "typemoney": "5" },
        { "type": 7, "typenum": "", "typemoney": "" }
      ]
    }
  ]
}
